project/__init__.py
project/main.py
project/data/__init__.py
project/data/address_book_functions.py
project/data/classes.py
project/data/global_declarations.py
project/data/notebook_functions.py
project/data/record.py
pipy_upload_test-0.6.dist-info/METADATA
pipy_upload_test-0.6.dist-info/WHEEL
pipy_upload_test-0.6.dist-info/entry_points.txt
pipy_upload_test-0.6.dist-info/top_level.txt
pipy_upload_test-0.6.dist-info/RECORD
