Metadata-Version: 2.1
Name: pipy_upload_test
Version: 0.6
Requires-Dist: prompt-toolkit
